Workbook

Sheet System Requirements
A1: Platform System Requirements
A2: One deployment on AWS. Five job-worker containers run at all times; everything else is a single shared service.
A4: AT A GLANCE
A5: Typical - what runs around the clock | D5: =Assumptions!$B$13+Assumptions!$B$19 -> 7 | G5: =Assumptions!$B$13*Assumptions!$B$14+Assumptions!$B$19*Assumptions!$B$21 -> 6 | H5: =Assumptions!$B$13*Assumptions!$B$15+Assumptions!$B$19*Assumptions!$B$22 -> 22 | K5: Five workers plus two web containers
A6: Peak - the busiest the platform gets | D6: =Assumptions!$B$13+Assumptions!$B$20 -> 9 | G6: =Assumptions!$B$13*Assumptions!$B$14+Assumptions!$B$20*Assumptions!$B$23 -> 9 | H6: =Assumptions!$B$13*Assumptions!$B$15+Assumptions!$B$20*Assumptions!$B$24 -> 28 | K6: Web tier scales; the five workers do not change
A8: Component | B8: What it actually runs | C8: AWS service | D8: How many | E8: Cores each | F8: GB each | G8: Cores total | H8: GB total | I8: Storage | J8: Needs code change? | K8: Note
A9: 1. BACKEND JOB WORKERS - the five always-running instances | K9: The requirement. Five containers, up around the clock.
A10: Job worker container | B10: Unpacks a tender, classifies documents, calls the model, stores the facts | C10: ECS Fargate task | D10: =Assumptions!$B$13 -> 5 | E10: =Assumptions!$B$14 -> 1 | F10: =Assumptions!$B$15 -> 4 | G10: =Assumptions!$B$13*Assumptions!$B$14 -> 5 | H10: =Assumptions!$B$13*Assumptions!$B$15 -> 20 | I10: - | J10: YES - C1, C2 | K10: One tender each, so five run in parallel. Size is fixed when the container starts.
A11: Extra workers on demand | B11: Started automatically when the queue backs up | C11: ECS Fargate task | D11: =Assumptions!$B$16 -> 0 | E11: =Assumptions!$B$14 -> 1 | F11: =Assumptions!$B$15 -> 4 | I11: - | J11: YES - C1 | K11: Optional. Five is the floor, not the ceiling. Set the count on the Assumptions tab.
A13: 2. WEB / API TIER - what people actually see | K13: Separate from the workers so a long job never blocks a screen.
A14: Web / API container | B14: uvicorn api.main:app plus the compiled React front end, one origin | C14: ECS Fargate task | D14: =Assumptions!$B$19 -> 2 | E14: =Assumptions!$B$21 -> 0.5 | F14: =Assumptions!$B$22 -> 1 | G14: =Assumptions!$B$19*Assumptions!$B$21 -> 1 | H14: =Assumptions!$B$19*Assumptions!$B$22 -> 2 | I14: - | J14: No | K14: Two is the availability floor - one container makes every deploy an outage.
A16: 3. STORAGE, QUEUE AND LOGS - one of each | K16: One organisation means one set. None of this is duplicated.
A17: System file store | B17: auth.json, workflow.json, bidders.db, the stored tenders | C17: EFS | D17: 1 | I17: =Assumptions!$B$35&" GB typical / "&Assumptions!$B$36&" GB peak" -> 50 GB typical / 200 GB peak | J17: YES - C4 | K17: The system of record. Shared by every container, so it cannot be local disk.
A18: Document store | B18: Every uploaded drawing, datasheet and vendor proposal | C18: S3 | D18: 1 | I18: =Assumptions!$B$33&" GB today / "&Assumptions!$B$34&" GB after a year" -> 0.5 GB today / 26 GB after a year | J18: YES - C3 | K18: Stored by a fingerprint of the contents, so the same file twice takes one copy.
A19: Job queue | B19: One message per tender, plus a dead-letter queue for poison documents | C19: SQS + DLQ | D19: 1 | I19: =Assumptions!$B$39&" million messages/month" -> 0.5 million messages/month | J19: YES - C1 | K19: How work gets from the web tier to the five workers.
A20: Logs | B20: Application logs, access logs, job outcomes | C20: CloudWatch Logs | D20: 1 | I20: =Assumptions!$B$37&" GB/month" -> 10 GB/month | J20: No | K20: Ingestion is the cost, not storage.
A22: 4. SHARED CLOUD SERVICES | K22: Supporting services. None of it scales with users.
A23: Load balancer | B23: One public entry point, TLS termination, health checks | C23: Application Load Balancer | D23: 1 | I23: - | J23: No | K23: Also what notices a sick container and stops sending it traffic.
A24: TLS certificate | B24: The https:// certificate | C24: ACM | D24: 1 | I24: - | J24: No | K24: Free with AWS-issued certificates, renews itself.
A25: DNS | B25: The hostname people type | C25: Route 53 | D25: 1 | I25: - | J25: No
A26: Image registry | B26: One image, used by both the workers and the web tier | C26: ECR | D26: 1 | I26: - | J26: No | K26: Build once, run everywhere. Workers and web differ only by start command.
A27: Container scheduler | B27: Places and restarts containers when they die | C27: ECS cluster (Fargate) | D27: 1 | I27: - | J27: No | K27: The cluster is free; you pay for the containers.
A28: Network | B28: One private network across two availability zones | C28: VPC | D28: 1 | I28: - | J28: No | K28: Containers have no public address.
A29: Internet egress | B29: Outbound HTTPS to the model provider | C29: NAT Gateway | D29: =Assumptions!$B$50 -> 2 | I29: - | J29: No | K29: The only thing the system phones out to. Billed hourly whether used or not.
A30: Private AWS access | B30: Image pulls, logs, secrets without crossing the internet | C30: VPC endpoints | D30: =Assumptions!$B$59 -> 8 | I30: - | J30: No | K30: Pays for itself by keeping that traffic off the NAT Gateway.
A31: Secret storage | B31: Model provider API key and app secrets | C31: Secrets Manager | D31: =Assumptions!$B$63 -> 3 | I31: - | J31: No | K31: Replaces baking the key into the image - see the Dockerfile's own warning.
A32: Monitoring | B32: Dashboards and alarms, including queue depth | C32: CloudWatch | D32: 1 | I32: - | J32: No | K32: Queue depth is the alarm that matters: it means work is arriving faster than five workers can clear it.
A33: Backup | B33: Scheduled snapshots of the file store | C33: AWS Backup | D33: 1 | I33: - | J33: No | K33: The store is the system of record. There is no second copy.
A35: 5. CHANGES THIS NEEDS IN THE SOFTWARE | K35: These cannot be bought. They have to be built.
A36: C1 | B36: Move tender processing out of the web request into the queue | C36: BLOCKS LAUNCH | K36: A tender is about 102 model calls in sequence, roughly 34 minutes. A load balancer closes an idle connection after 60 seconds, so the browser's request dies long before the work finishes.
A37: C2 | B37: Replace the in-process job lock with a shared one | C37: BLOCKS LAUNCH | K37: The guard that stops one tender being processed twice lives inside a single Python process. With five workers, two of them can start the same tender and overwrite each other.
A38: C3 | B38: Implement the S3 document store | C38: BLOCKS LAUNCH | K38: Documents are written to local disk today, which no other container can read. The storage interface was written expecting this, so it is a new class rather than a redesign.
A39: C4 | B39: Decide how the bidder registry is written | C39: Workaround available | K39: It is a SQLite file, and SQLite on shared network storage with several writers can corrupt. Free fix: route registry writes through one nominated worker. Durable fix: a managed database.
A40: C5 | B40: Add token metering | C40: Billing only | K40: Nothing counts the tokens spent. Costs here can be budgeted but not attributed to a department or a project.
A42: 6. DELIBERATELY NOT INCLUDED | K42: Things a reader may expect, and why each is absent.
A43: Separate web server (nginx) | B43: The image already serves the API and the front end from one process and one address.
A44: Managed database (RDS) | B44: Every store is a file today. Only needed if C4 is solved by moving to a database.
A45: Cache layer (Redis) | B45: There is no cache in the software, and nothing here is read-heavy enough to need one.
A46: CDN (CloudFront) | B46: The front-end bundle is small and served from the same address as the API.
A47: GPU capacity | B47: No model runs on our own hardware. Every model call is an outbound request to the provider.
A48: Kubernetes (EKS) | B48: About $75/month of control plane plus real operational burden, to schedule seven containers.
A49: Per-user or per-department isolation | B49: One organisation, one shared store. Access is controlled inside the application, not by separate infrastructure.
A51: Sizing note: the workers are sized for memory, not processor. About 99% of a tender run is spent waiting on the model provider's API,
A52: so processor use barely moves. What does move is memory - parsing a 220,000-character proposal, and loading a 1,346-row vendor spreadsheet.

Sheet Cost
A1: Running Cost
A2: One deployment, per month. Typical is a normal month; peak is the busiest the platform gets, held for a whole month.
A3: Every rate comes from the Assumptions tab. Nothing on this page is typed in by hand.
C5: TYPICAL $ / month | D5: PEAK $ / month
A6: TOTAL - everything, per month | C6: =C49 -> 615.21917 | D6: =D49 -> 1384.8067
A7: TOTAL - everything, per year | C7: =C49*12 -> 7382.63 | D7: =D49*12 -> 16617.68
A8: of which cloud services | C8: =C40 -> 453.3756 | D8: =D40 -> 737.4324 | E8: ="Rented by the hour - "&TEXT(C40/C49,"0%")&" of a typical month" -> Rented by the hour - 74% of a typical month
A9: of which the model API | C9: =C42 -> 161.84357 | D9: =D42 -> 647.37427 | E9: ="Charged per document - "&TEXT(C42/C49,"0%")&" of a typical month" -> Charged per document - 26% of a typical month
A11: Line item | B11: How it is worked out | C11: Typical $ / month | D11: Peak $ / month | E11: Note
A12: 1. BACKEND JOB WORKERS | C12: =C13+C14 -> 212.649 | D12: =D13+D14 -> 212.649 | E12: The five always-running containers - a fixed cost, identical in both columns
A13: Five job workers | B13: =Assumptions!$B$13&" containers x "&Assumptions!$B$14&" core / "&Assumptions!$B$15&" GB x "&Assumptions!$B$6&" hours" -> 5 containers x 1 core / 4 GB x 730 hours | C13: =(Assumptions!$B$13*(Assumptions!$B$14*Assumptions!$B$43+Assumptions!$B$15*Assumptions!$B$44)*Assumptions!$B$6) -> 212.649 | D13: =(Assumptions!$B$13*(Assumptions!$B$14*Assumptions!$B$43+Assumptions!$B$15*Assumptions!$B$44)*Assumptions!$B$6) -> 212.649 | E13: Up around the clock, busy or not. This is what 'always running' costs.
A14: Extra workers on demand | B14: =Assumptions!$B$16&" extra containers" -> 0 extra containers | C14: =Assumptions!$B$16*(Assumptions!$B$14*Assumptions!$B$43+Assumptions!$B$15*Assumptions!$B$44)*Assumptions!$B$6 -> 0 | D14: =Assumptions!$B$16*(Assumptions!$B$14*Assumptions!$B$43+Assumptions!$B$15*Assumptions!$B$44)*Assumptions!$B$6 -> 0 | E14: Zero unless you set a count. Each extra worker costs the same as one of the five.
A16: 2. WEB / API TIER | C16: =C17 -> 36.0401 | D16: =D17 -> 144.1604 | E16: Scales with how many people are using the screens
A17: Web/API containers | B17: =Assumptions!$B$19&" containers typical, "&Assumptions!$B$20&" at peak" -> 2 containers typical, 4 at peak | C17: =(Assumptions!$B$19*(Assumptions!$B$21*Assumptions!$B$43+Assumptions!$B$22*Assumptions!$B$44)*Assumptions!$B$6) -> 36.0401 | D17: =(Assumptions!$B$20*(Assumptions!$B$23*Assumptions!$B$43+Assumptions!$B$24*Assumptions!$B$44)*Assumptions!$B$6) -> 144.1604 | E17: Two is the availability floor; more only when people are actually on it.
A19: 3. STORAGE, QUEUE AND LOGS | C19: =SUM(C20:C23) -> 20.5115 | D19: =SUM(D20:D23) -> 82.598 | E19: One set for the whole platform
A20: System file store (EFS) | B20: =Assumptions!$B$35&" GB x $"&Assumptions!$B$54&" per GB" -> 50 GB x $0.3 per GB | C20: =Assumptions!$B$35*Assumptions!$B$54 -> 15 | D20: =Assumptions!$B$36*Assumptions!$B$54 -> 60 | E20: The expensive storage tier, and why bulk documents belong in S3 instead.
A21: Document store (S3) | B21: =Assumptions!$B$33&" GB today, "&Assumptions!$B$34&" GB after a year" -> 0.5 GB today, 26 GB after a year | C21: =Assumptions!$B$33*Assumptions!$B$55 -> 0.0115 | D21: =Assumptions!$B$34*Assumptions!$B$55 -> 0.598 | E21: Thirteen times cheaper per GB than the file store, and it never runs out of room.
A22: Job queue (SQS) | B22: =Assumptions!$B$39&" million messages x $"&Assumptions!$B$65 -> 0.5 million messages x $0.4 | C22: =Assumptions!$B$39*Assumptions!$B$65 -> 0.2 | D22: =Assumptions!$B$40*Assumptions!$B$65 -> 0.8 | E22: Effectively free at this scale.
A23: Logs (CloudWatch) | B23: =Assumptions!$B$37&" GB ingested and stored" -> 10 GB ingested and stored | C23: =Assumptions!$B$37*(Assumptions!$B$56+Assumptions!$B$57) -> 5.3 | D23: =Assumptions!$B$38*(Assumptions!$B$56+Assumptions!$B$57) -> 21.2 | E23: Ingestion is the cost, not storage.
A25: 4. SHARED CLOUD SERVICES | C25: =SUM(C26:C34) -> 184.175 | D25: =SUM(D26:D34) -> 298.025 | E25: Supporting services - largely flat whatever happens
A26: Load balancer | B26: ="$"&Assumptions!$B$45&" per hour plus capacity units" -> $0.0225 per hour plus capacity units | C26: =(Assumptions!$B$45+Assumptions!$B$47*Assumptions!$B$46)*Assumptions!$B$6 -> 45.625 | D26: =(Assumptions!$B$45+Assumptions!$B$48*Assumptions!$B$46)*Assumptions!$B$6 -> 133.225 | E26: One public entry point for the whole platform.
A27: NAT Gateways | B27: =Assumptions!$B$50&" zones x $"&Assumptions!$B$49&" per hour plus data" -> 2 zones x $0.045 per hour plus data | C27: =Assumptions!$B$50*Assumptions!$B$49*Assumptions!$B$6+Assumptions!$B$52*Assumptions!$B$51 -> 67.95 | D27: =Assumptions!$B$50*Assumptions!$B$49*Assumptions!$B$6+Assumptions!$B$53*Assumptions!$B$51 -> 79.2 | E27: Billed hourly whether traffic flows or not. One zone halves it and costs resilience.
A28: VPC endpoints | B28: =Assumptions!$B$59&" endpoints x $"&Assumptions!$B$58&" per hour" -> 8 endpoints x $0.01 per hour | C28: =Assumptions!$B$59*Assumptions!$B$58*Assumptions!$B$6 -> 58.4 | D28: =Assumptions!$B$59*Assumptions!$B$58*Assumptions!$B$6 -> 58.4 | E28: Pays for itself by keeping image pulls and logs off the NAT Gateway.
A29: Image registry (ECR) | B29: =Assumptions!$B$61&" GB x $"&Assumptions!$B$60 -> 5 GB x $0.1 | C29: =Assumptions!$B$61*Assumptions!$B$60 -> 0.5 | D29: =Assumptions!$B$61*Assumptions!$B$60 -> 0.5 | E29: One image for every container.
A30: DNS (Route 53) | B30: One hosted zone | C30: =Assumptions!$B$64 -> 0.5 | D30: =Assumptions!$B$64 -> 0.5
A31: Secret storage | B31: =Assumptions!$B$63&" secrets x $"&Assumptions!$B$62 -> 3 secrets x $0.4 | C31: =Assumptions!$B$63*Assumptions!$B$62 -> 1.2 | D31: =Assumptions!$B$63*Assumptions!$B$62 -> 1.2 | E31: Keeps the provider key out of the image.
A32: Container scheduler (ECS) | B32: Fargate cluster | C32: 0 | D32: 0 | E32: No charge for the cluster itself.
A33: TLS certificate (ACM) | B33: AWS-issued, renews itself | C33: 0 | D33: 0 | E33: No charge.
A34: Backup and snapshots | B34: Flat estimate | C34: =Assumptions!$B$66 -> 10 | D34: =Assumptions!$B$67 -> 25 | E34: The store is the system of record. Not an optional line.
A36: 5. ADJUSTMENTS | C36: =SUM(C37:C38) -> 0 | D36: =SUM(D37:D38) -> 0 | E36: Both are zero until you change a lever on the Assumptions tab
A37: Region uplift | B37: ="Multiplier "&TEXT(Assumptions!$B$86,"0.00")&" on sections 1 to 4" -> Multiplier 1.00 on sections 1 to 4 | C37: =(C12+C16+C19+C25)*(Assumptions!$B$86-1) -> 0 | D37: =(D12+D16+D19+D25)*(Assumptions!$B$86-1) -> 0 | E37: Set to about 1.15-1.20 to price the UAE region instead of Virginia.
A38: Compute Savings Plan | B38: ="Discount "&TEXT(Assumptions!$B$87,"0%")&" on container lines only" -> Discount 0% on container lines only | C38: =-((Assumptions!$B$13*(Assumptions!$B$14*Assumptions!$B$43+Assumptions!$B$15*Assumptions!$B$44)*Assumptions!$B$6)+(Assumptions!$B$19*(Assumptions!$B$21*Assumptions!$B$43+Assumptions!$B$22*Assumptions!$B$44)*Assumptions!$B$6))*Assumptions!$B$87 -> 0 | D38: =-((Assumptions!$B$13*(Assumptions!$B$14*Assumptions!$B$43+Assumptions!$B$15*Assumptions!$B$44)*Assumptions!$B$6)+(Assumptions!$B$20*(Assumptions!$B$23*Assumptions!$B$43+Assumptions!$B$24*Assumptions!$B$44)*Assumptions!$B$6))*Assumptions!$B$87 -> 0 | E38: Five always-on containers are exactly what a Savings Plan is for.
A40: CLOUD SERVICES SUBTOTAL | C40: =C12+C16+C19+C25+C36 -> 453.3756 | D40: =D12+D16+D19+D25+D36 -> 737.4324 | E40: Sections 1 to 5
A42: 6. MODEL API | C42: =C46+C47 -> 161.84357 | D42: =D46+D47 -> 647.37427 | E42: Not an AWS cost. Charged per document read, not per hour.
A43: Documents processed | B43: Weekly volume x weeks in the month | C43: =(Assumptions!$B$27*Assumptions!$B$7) -> 2166.6667 | D43: =(Assumptions!$B$28*Assumptions!$B$7) -> 8666.6667 | E43: MB per month
A44: Input tokens | B44: Document text plus prompt overhead, at measured rates | C44: =((Assumptions!$B$27*Assumptions!$B$7)*Assumptions!$B$78*Assumptions!$B$79/Assumptions!$B$80/1000000) -> 17.176197 | D44: =((Assumptions!$B$28*Assumptions!$B$7)*Assumptions!$B$78*Assumptions!$B$79/Assumptions!$B$80/1000000) -> 68.704789 | E44: Millions of tokens per month
A45: Output tokens | B45: Extracted facts written back as structured data | C45: =((Assumptions!$B$27*Assumptions!$B$7)*Assumptions!$B$78*Assumptions!$B$81*Assumptions!$B$82/Assumptions!$B$83/1000000) -> 5.9469963 | D45: =((Assumptions!$B$28*Assumptions!$B$7)*Assumptions!$B$78*Assumptions!$B$81*Assumptions!$B$82/Assumptions!$B$83/1000000) -> 23.787985 | E45: Millions of tokens per month
A46: Model calls at list price | B46: Input and output tokens at the per-million rates | C46: =((Assumptions!$B$27*Assumptions!$B$7)*Assumptions!$B$78*Assumptions!$B$79/Assumptions!$B$80/1000000)*(Assumptions!$B$70*(1-Assumptions!$B$74)+Assumptions!$B$72*Assumptions!$B$74)+((Assumptions!$B$27*Assumptions!$B$7)*Assumptions!$B$78*Assumptions!$B$81*Assumptions!$B$82/Assumptions!$B$83/1000000)*(Assumptions!$B$71*(1-Assumptions!$B$74)+Assumptions!$B$73*Assumptions!$B$74) -> 140.73354 | D46: =((Assumptions!$B$28*Assumptions!$B$7)*Assumptions!$B$78*Assumptions!$B$79/Assumptions!$B$80/1000000)*(Assumptions!$B$70*(1-Assumptions!$B$74)+Assumptions!$B$72*Assumptions!$B$74)+((Assumptions!$B$28*Assumptions!$B$7)*Assumptions!$B$78*Assumptions!$B$81*Assumptions!$B$82/Assumptions!$B$83/1000000)*(Assumptions!$B$71*(1-Assumptions!$B$74)+Assumptions!$B$73*Assumptions!$B$74) -> 562.93415 | E46: Sonnet 5 by default. Set the Opus share on the Assumptions tab.
A47: Failed and retried calls | B47: ="+"&TEXT(Assumptions!$B$75,"0%")&" of the line above" -> +15% of the line above | C47: =C46*Assumptions!$B$75 -> 21.11003 | D47: =D46*Assumptions!$B$75 -> 84.440122 | E47: A chunk that hits the output ceiling fails the same way twice, so both attempts are billed.
A49: GRAND TOTAL - per month | C49: =C40+C42 -> 615.21917 | D49: =D40+D42 -> 1384.8067 | E49: Cloud services plus the model API
A51: 7. WAYS TO SPEND LESS | C51: - | D51: - | E51: Not included in the totals above. Figures are the saving.
A52: Use the batch service for tender processing | B52: Halves every model-API line | C52: =-C42*0.5 -> -80.921783 | D52: =-D42*0.5 -> -323.68713 | E52: Processing already runs in the background, so the only cost is slower turnaround.
A53: Move documents to S3 (change C3) | B53: Storage at $0.023 instead of $0.30 per GB | C53: =-(Assumptions!$B$33*(Assumptions!$B$54-Assumptions!$B$55)) -> -0.1385 | D53: =-(Assumptions!$B$34*(Assumptions!$B$54-Assumptions!$B$55)) -> -7.202 | E53: Also removes the shared-storage risk in change C4.
A54: 1-year Compute Savings Plan | B54: About 17% off always-on containers | C54: =-((Assumptions!$B$13*(Assumptions!$B$14*Assumptions!$B$43+Assumptions!$B$15*Assumptions!$B$44)*Assumptions!$B$6)+(Assumptions!$B$19*(Assumptions!$B$21*Assumptions!$B$43+Assumptions!$B$22*Assumptions!$B$44)*Assumptions!$B$6))*0.17 -> -42.277147 | D54: =-((Assumptions!$B$13*(Assumptions!$B$14*Assumptions!$B$43+Assumptions!$B$15*Assumptions!$B$44)*Assumptions!$B$6)+(Assumptions!$B$20*(Assumptions!$B$23*Assumptions!$B$43+Assumptions!$B$24*Assumptions!$B$44)*Assumptions!$B$6))*0.17 -> -60.657598 | E54: Set the discount lever on the Assumptions tab to fold this into the totals.
A55: Run the five workers on Spot capacity | B55: About 70% off the worker line | C55: =-(Assumptions!$B$13*(Assumptions!$B$14*Assumptions!$B$43+Assumptions!$B$15*Assumptions!$B$44)*Assumptions!$B$6)*0.7 -> -148.8543 | D55: =-(Assumptions!$B$13*(Assumptions!$B$14*Assumptions!$B$43+Assumptions!$B$15*Assumptions!$B$44)*Assumptions!$B$6)*0.7 -> -148.8543 | E55: An interrupted job returns to the queue and another worker takes it. The web tier stays on-demand.
A56: Drop to one NAT Gateway | B56: One availability zone instead of two | C56: =-Assumptions!$B$49*Assumptions!$B$6 -> -32.85 | D56: =-Assumptions!$B$49*Assumptions!$B$6 -> -32.85 | E56: Cheapest saving here, and the only one that buys a worse system. Not recommended.
A58: Reading the two columns: 'typical' is a normal month. 'Peak' assumes the busiest the platform gets, held for a full month,
A59: which no month ever does. It is a budget ceiling, not a forecast. See the next tab for how it is built.
A60: Prices are us-east-1 list prices copied by hand and will go stale. Check them before quoting anything.

Sheet How Peak Is Calculated
A1: How the peak figure is worked out
A2: A plain-English guide. No cloud knowledge needed - the technical detail is at the end for those who want it.
A4: 1. The short answer
A5: The peak figure assumes the platform is as busy as it can possibly get, and that it stays that way
A6: for every single hour of the month.
A8: It is a ceiling - the most this could ever cost. It is not what we expect the bill to be.
A10: 2. A way to picture it
A11: Imagine you hire delivery vans.
A13: On a normal day you need 3 vans.
A14: On your busiest afternoon of the year you need 7.
A16: The peak figure is the cost of hiring all 7 - and keeping every one of them for the whole month,
A17: including the weeks you only ever needed 3.
... A22: 3. What changes between a normal month and a peak one
A23: What changes | B23: Normal month | C23: Peak | D23: What that means in plain terms
A24: The five job workers | B24: 5 running | C24: 5 running | D24: NO CHANGE. They are always on. This is the fixed part of the bill.
A25: Tenders being processed | B25: 1 at a time | C25: 5 at a time | D25: The same five workers, all busy instead of mostly idle. Costs nothing extra.
A26: Web containers | B26: 2 | C26: 4 | D26: More people on the screens at once, so more copies serve them
A27: Documents arriving | B27: 500 MB/week | C27: 2,000 MB/week | D27: Four times the paperwork - the biggest single driver
A28: Storage used | B28: 50 GB | C28: 200 GB | D28: More documents held, and more history kept
A29: How long it lasts | B29: a few hours | C29: all 730 hours | D29: The rush never ends - it runs from the 1st to the 31st
A31: The first row is the important one.
A32: Because five workers run around the clock either way, being busy does not cost more than being idle.
A33: You have already paid for the capacity. What actually pushes the peak figure up is the volume of
A34: documents arriving, because reading them is charged per document.
A36: 4. The two kinds of cost - and this is the part worth understanding
A37: Cloud services | B37: Rented by the hour, like a hire car. | D37: You pay for time. An idle container costs the same as a busy one.
A38: Reading the documents | B38: Charged per document, like postage. | D38: You pay only for what you actually send. Idle costs nothing at all.
A40: So a quiet month is cheap on the reading half and unchanged on the cloud half. A busy month costs
A41: more almost entirely because more documents genuinely arrived - not because the servers worked harder.
A43: 5. One line, worked all the way through
A44: Take the five job workers - the programs that read a tender: they open each vendor's documents, send
A45: them to the AI to be read, and store what comes back.
B47: Normal month | C47: Peak
A48: How many are running | B48: =Assumptions!$B$13 -> 5 | C48: =Assumptions!$B$13 -> 5 | D48: Always five - that is the requirement
A49: Processor cores each | B49: =Assumptions!$B$14 -> 1 | C49: =Assumptions!$B$14 -> 1 | D49: Fixed when the container starts - it cannot be resized while running
A50: Memory each (GB) | B50: =Assumptions!$B$15 -> 4 | C50: =Assumptions!$B$15 -> 4 | D50: Enough to hold a 220,000-character proposal while reading it
A51: Cost per core, per hour | B51: =Assumptions!$B$43 -> 0.04048 | C51: =Assumptions!$B$43 -> 0.04048 | D51: Set by Amazon
A52: Cost per GB, per hour | B52: =Assumptions!$B$44 -> 0.004445 | C52: =Assumptions!$B$44 -> 0.004445 | D52: Set by Amazon
A53: Hours in the month | B53: =Assumptions!$B$6 -> 730 | C53: =Assumptions!$B$6 -> 730 | D53: They run for every one of them
A54: COST FOR THE MONTH | B54: =(Assumptions!$B$13*(Assumptions!$B$14*Assumptions!$B$43+Assumptions!$B$15*Assumptions!$B$44)*Assumptions!$B$6) -> 212.649 | C54: =(Assumptions!$B$13*(Assumptions!$B$14*Assumptions!$B$43+Assumptions!$B$15*Assumptions!$B$44)*Assumptions!$B$6) -> 212.649 | D54: workers x (cores x core price + memory x memory price) x hours
A56: Identical in both columns, because five workers run either way. Every other line on the Cost tab uses
A57: the same arithmetic - only the numbers change.
A59: 6. What it adds up to
B60: Normal month | C60: Peak | D60: Peak is this many times bigger
A61: Everything, per month | B61: =Cost!C49 -> 615.21917 | C61: =Cost!D49 -> 1384.8067 | D61: =Cost!D49/Cost!C49 -> 2.250916
A62: Everything, per year | B62: =Cost!C49*12 -> 7382.63 | C62: =Cost!D49*12 -> 16617.68
A63: Cloud services (rented by the hour) | B63: =Cost!C40 -> 453.3756 | C63: =Cost!D40 -> 737.4324 | D63: =Cost!D40/Cost!C40 -> 1.6265375
A64: Reading the documents (charged per document) | B64: =Cost!C42 -> 161.84357 | C64: =Cost!D42 -> 647.37427 | D64: =Cost!D42/Cost!C42 -> 4
A66: 7. What a realistically busy month looks like
A67: The peak figure holds the rush for all 730 hours. Change the two numbers below and see what happens.
A69: Hours of the month spent at full stretch | B69: 73 | C69: out of 730 | D69: Type a different number here. 73 hours is about 10% of the month, or three full days.
A70: Documents that month, against a normal month | B70: 1.5 | C70: x | D70: 1.0 = a normal month's paperwork. 4.0 = the peak column's.
B72: That month would cost
A73: Cloud services | B73: =Cost!C40+(Cost!D40-Cost!C40)*B69/Assumptions!$B$6 -> 481.78128 | D73: Quiet rate for the calm hours, full rate for the busy ones
A74: Reading the documents | B74: =Cost!C42*B70 -> 242.76535 | D74: Scales straight with how many documents actually arrived
A75: A REALISTIC BUSY MONTH | B75: =B73+B74 -> 724.54663 | D75: Compare with the two figures in section 6
A76: more than a normal month | B76: =B75-Cost!C49 -> 109.32746
A77: less than the peak ceiling | B77: =Cost!D49-B75 -> 660.26004
A79: 8. What this number is for - and what it is not
A80: Use it for | C80: Do not use it for
A81: Setting a budget ceiling nobody can exceed | C81: Forecasting next month's invoice
A82: Answering "what is the most this could cost?" | C82: Deciding what to charge for the service
A83: Checking the design survives the busiest week | C83: Buying capacity in advance
A85: Nothing here is bought up front. Because the cloud is rented by the hour, the peak figure is only ever
A86: paid if the peak actually happens - and if it never does, it never costs a penny.
A88: 9. Plain-English glossary
A89: Term | B89: What it means
A90: Instance | B90: One running container in the backend. Five job workers run at all times - those are the five instances.
A91: Container | B91: One running copy of the software. Several run at once so the system stays up and gets through work faster.
A92: Job worker | B92: The container that reads a tender: opens the documents, sends them to the AI, stores what comes back.
A93: Web / API tier | B93: The containers that serve the screens people actually look at. Kept separate so a long job never blocks a page.
A94: Core / vCPU | B94: A unit of processing power, rented by the hour. Half a core is plenty for work that mostly sits waiting.
A95: GB (memory) | B95: Working space the software needs while it has a document open. Also rented by the hour.
A96: Queue | B96: A waiting list of jobs. The web tier adds to it; the five workers take from it, one tender each.
A97: Fargate | B97: Amazon's way of running containers without renting whole machines. You pay only for the containers.
A98: Load balancer | B98: The single front door. Takes each visitor to a healthy web container.
A99: Document store (S3) | B99: Where the uploaded documents are kept. Very cheap, and it never runs out of room.
A100: File store (EFS) | B100: Faster storage for the system's own records - accounts, workflow, the bidder list.
... A102: Token | B102: How AI reading is measured and billed - roughly three characters of text. More pages, more tokens.
A104: Where these numbers come from: the Assumptions tab holds every figure used here. Change one there and this page updates with it.
A105: Prices are Amazon's published US prices, copied by hand, and will go out of date. Check them before quoting anything.

Sheet Assumptions
A1: Assumptions & Rates
A2: Every number the other tabs use lives here. Blue = change it. The Basis column says whether a figure was measured or estimated.
A4: Item | B4: Value | C4: Unit | D4: Basis
A5: SCALE - one platform, one organisation
A6: Hours per month | B6: 730 | C6: hours | D6: 365 x 24 / 12
A7: Weeks per month | B7: 4.3333333 | C7: weeks | D7: 52 / 12
A8: People who can sign in | B8: 50 | C8: users | D8: Agreed
A9: Signed in at the same time - typical | B9: 10 | C9: users | D9: ESTIMATED
A10: Signed in at the same time - peak | B10: 50 | C10: users | D10: Everyone at once
A12: BACKEND JOB WORKERS - the five always-running instances
A13: Job workers running at all times | B13: 5 | C13: containers | D13: The requirement: five, always up
A14: Processor cores per worker | B14: 1 | C14: vCPU | D14: Fixed when the container starts - cannot change while running
A15: Memory per worker | B15: 4 | C15: GB | D15: Sized for the largest job: a 220k-character proposal
A16: Extra workers if the queue backs up | B16: 0 | C16: containers | D16: Optional scale-out beyond the five. Cost shown separately.
A18: WEB / API TIER - serves the screens and the API
A19: Web/API containers - typical | B19: 2 | C19: containers | D19: Two zones - the availability floor, not scale
A20: Web/API containers - peak | B20: 4 | C20: containers | D20: ESTIMATED - scales on request load
A21: Processor cores each - typical | B21: 0.5 | C21: vCPU | D21: Mostly waiting on I/O
A22: Memory each - typical | B22: 1 | C22: GB | D22: FastAPI plus the compiled front end
A23: Processor cores each - peak | B23: 1 | C23: vCPU | D23: ESTIMATED
A24: Memory each - peak | B24: 2 | C24: GB | D24: Upload buffering
A26: WORKLOAD
A27: Documents arriving - typical | B27: 500 | C27: MB/week | D27: MEASURED - docs/pricing/consumption-model.md
A28: Documents arriving - peak | B28: 2000 | C28: MB/week | D28: ESTIMATED - bid-deadline week, 4x typical
A29: Tenders processed at once - typical | B29: 1 | C29: jobs | D29: Four of the five workers idle but warm
A30: Tenders processed at once - peak | B30: 5 | C30: jobs | D30: All five workers busy - the design point
A32: STORAGE - one set, not one per anything
A33: Document store - today | B33: 0.5 | C33: GB | D33: YOUR FIGURE - 500 MB of RFQ documents
A34: Document store - after a year | B34: 26 | C34: GB | D34: MEASURED rate - 500 MB/week accumulating
A35: System file store - typical | B35: 50 | C35: GB | D35: ESTIMATED - accounts, workflow, bidder registry
A36: System file store - peak | B36: 200 | C36: GB | D36: ESTIMATED
A37: Log volume - typical | B37: 10 | C37: GB/month | D37: ESTIMATED
A38: Log volume - peak | B38: 40 | C38: GB/month | D38: ESTIMATED
A39: Queue messages - typical | B39: 0.5 | C39: millions/mo | D39: ESTIMATED
A40: Queue messages - peak | B40: 2 | C40: millions/mo | D40: ESTIMATED
A42: AWS PRICES - us-east-1, on-demand list price (hand-copied, goes stale)
A43: Fargate - per core-hour | B43: 0.04048 | C43: $ | D43: AWS list price
A44: Fargate - per GB-hour | B44: 0.004445 | C44: $ | D44: AWS list price
A45: Load balancer - per hour | B45: 0.0225 | C45: $ | D45: AWS list price
A46: Load balancer - per capacity unit-hour | B46: 0.008 | C46: $ | D46: AWS list price
A47: Load balancer capacity units - typical | B47: 5 | C47: LCU | D47: ESTIMATED
A48: Load balancer capacity units - peak | B48: 20 | C48: LCU | D48: ESTIMATED
A49: NAT Gateway - per hour, per zone | B49: 0.045 | C49: $ | D49: AWS list price
A50: NAT Gateways (one per zone) | B50: 2 | C50: count | D50: Two zones for resilience
A51: NAT Gateway - per GB processed | B51: 0.045 | C51: $ | D51: AWS list price
A52: NAT GB/month - typical | B52: 50 | C52: GB | D52: ESTIMATED
A53: NAT GB/month - peak | B53: 300 | C53: GB | D53: ESTIMATED
A54: EFS Standard - per GB-month | B54: 0.3 | C54: $ | D54: AWS list price
... A67: Backup and snapshots - peak | B67: 25 | C67: $/month | D67: ESTIMATED
A69: MODEL API PRICES - list price, verify before quoting
A70: Sonnet 5 - input per million tokens | B70: 3 | C70: $ | D70: LIST PRICE - goes stale
A71: Sonnet 5 - output per million tokens | B71: 15 | C71: $ | D71: LIST PRICE - goes stale
A72: Opus 5 - input per million tokens | B72: 5 | C72: $ | D72: LIST PRICE - goes stale
A73: Opus 5 - output per million tokens | B73: 25 | C73: $ | D73: LIST PRICE - goes stale
A74: Share of work sent to Opus | B74: 0 | C74: fraction | D74: 0 = all Sonnet. Try 0.5 to see the effect.
A75: Failed and retried calls | B75: 0.15 | C75: fraction | D75: ESTIMATED - typical; 0.30 on a bad week
A77: TOKEN MODEL - measured by replaying a real tender
A78: Characters per MB of source document | B78: 18470 | C78: chars | D78: MEASURED - 818,229 chars from 44.3 MB
A79: Input ratio (prompts plus chunk overhead) | B79: 1.4636 | C79: x | D79: MEASURED
A80: Characters per input token | B80: 3.41 | C80: chars | D80: MEASURED
A81: Output ratio | B81: 0.2662 | C81: x | D81: MEASURED - stored compact JSON
A82: Output allowance | B82: 1.15 | C82: x | D82: ESTIMATED
A83: Characters per output token | B83: 2.06 | C83: chars | D83: MEASURED
A85: LEVERS
A86: Region price multiplier | B86: 1 | C86: x | D86: 1.00 = us-east-1. UAE is roughly 1.15-1.20
A87: Compute Savings Plan discount | B87: 0 | C87: fraction | D87: 1-year, no upfront is typically 0.15-0.20
